Metadata-Version: 2.1
Name: easyeval-tool
Version: 0.0.1
Summary: EasyEval
Home-page: https://github.com/zjunlp/EasyEval/tree/main
Author: Yida Xue
Author-email: xueyida@qq.com
License: UNKNOWN
Keywords: AI,NLP,instruction,language model
Platform: UNKNOWN
Classifier: Programming Language :: Python :: 3.7
Classifier: Programming Language :: Python :: 3.8
Classifier: Programming Language :: Python :: 3.9
Classifier: Programming Language :: Python :: 3.10
Classifier: Programming Language :: Python :: 3.11
Classifier: Intended Audience :: Developers
Classifier: Intended Audience :: Education
Classifier: Intended Audience :: Science/Research
Requires-Python: >=3.7.0
